{
    "homepage": "http://arctime.cn/index.html",
    "version": "2.3",
    "license": "Freeware",
    "architecture": {
        "64bit": {
            "url": "https://dlhz.arctime.cn/ARCTIME_PRO_2.3_WIN32.rar"
        },
        "32bit": {
            "url": "https://dlhz.arctime.cn/ARCTIME_PRO_2.3_WIN32.rar"
        },
        "hash": "download"
    },
    "checkver": {
        "url": "http://arctime.cn/download.html",
        "re": "Pro ([\\d.]+)"
    },
    "autoupdate": {
        "architecture": {
            "64bit": {
                "url": "https://dlhz.arctime.cn/ARCTIME_PRO_$version_WIN64.rar"
            },
            "32bit": {
                "url": "https://dlhz.arctime.cn/ARCTIME_PRO_$version_WIN64.rar"
            },
            "hash": "download"
        }
    }
}
