{
    "homepage": "https://www.bypass.cn",
    "description": "12306 ticket buyer",
    "version": "1.13.98",
    "license": "Freeware",
    "url": "https://www.bypass.cn/api/download?name=Bypass.zip#/Bypass.zip",
    "hash": "68800dc30c9ee8de6fe78a3ce1cd085b927ff11a02f6fcdb67e5ae67e334da10",
    "extract_dir": "Bypass",
    "bin": [
        [
            "Bypass.exe",
            "bypass"
        ]
    ],
    "checkver": {
        "url": "https://www.bypass.cn/",
        "regex": "Version.*?([\\d.]+)</label>"
    },
    "autoupdate": {
        "url": "https://www.bypass.cn/api/download?name=Bypass.zip#/Bypass.zip",
        "hash": {
            "mode": "download"
        }
    }
}
